{
  "book_usfm": "AMO",
  "name": "Amós",
  "local_title": "Biblia Dios Habla Hoy",
  "local_abbreviation": "DHH94I",
  "version_id": 52,
  "publisher": {
    "name": "United Bible Societies"
  },
  "copyright": {
    "html": "<p>Texto © Sociedades Bíblicas Unidas, 1994.</p>",
    "text": "Texto © Sociedades Bíblicas Unidas, 1994."
  },
  "language": {
    "iso_639_1": "es",
    "iso_639_3": "spa",
    "language_tag": "spa",
    "local_name": "Español (América Latina)",
    "text_direction": "ltr"
  },
  "repository": "https://github.com/mrk214/bible-data-es-spa",
  "chapters": [
    {
      "chapter_usfm": "AMO.1",
      "is_chapter": true,
      "current": {
        "usfm": [
          "AMO.1"
        ],
        "human": "Amós 1"
      },
      "next": {
        "canonical": true,
        "usfm": [
          "AMO.2"
        ],
        "human": "Amós 2",
        "toc": true
      },
      "previous": {
        "canonical": true,
        "usfm": [
          "JOL.3"
        ],
        "human": "Joel 3",
        "toc": true
      },
      "items": [
        {
          "type": "heading2",
          "verse_numbers": [],
          "lines": [
            "I. PRÓLOGO"
          ],
          "rlw_lines": []
        },
        {
          "type": "section2",
          "verse_numbers": [],
          "lines": [
            "(1.1-2)"
          ],
          "rlw_lines": []
        },
        {
          "type": "verse",
          "verse_numbers": [
            1
          ],
          "lines": [
            "Este es el mensaje que Amós, pastor de ovejas del poblado de Tecoa, recibió de parte de Dios acerca de Israel, dos años antes del terremoto, en tiempos de Ozías, rey de Judá, y de Jeroboam, hijo de Joás, rey de Israel."
          ],
          "rlw_lines": []
        },
        {
          "type": "verse",
          "verse_numbers": [
            2
          ],
          "lines": [
            "Cuando el Señor hace oír su voz de trueno",
            "desde el monte Sión, en Jerusalén,",
            "las tierras de pastos se marchitan",
            "y se reseca la cumbre del Carmelo."
          ],
          "rlw_lines": []
        },
        {
          "type": "heading2",
          "verse_numbers": [],
          "lines": [
            "II. ORÁCULOS CONTRA LAS NACIONES Y CONTRA EL PUEBLO DE ISRAEL"
          ],
          "rlw_lines": []
        },
        {
          "type": "section2",
          "verse_numbers": [],
          "lines": [
            "(1.3—2.16)"
          ],
          "rlw_lines": []
        },
        {
          "type": "heading1",
          "verse_numbers": [],
          "lines": [
            "Juicios sobre las naciones vecinas"
          ],
          "rlw_lines": []
        },
        {
          "type": "verse",
          "verse_numbers": [
            3
          ],
          "lines": [
            "Así dice el Señor:",
            "«Los de Damasco han cometido tantas maldades",
            "que no dejaré de castigarlos;",
            "pues trillaron a los de Galaad con trillos de hierro."
          ],
          "rlw_lines": []
        },
        {
          "type": "verse",
          "verse_numbers": [
            4
          ],
          "lines": [
            "Por eso pondré fuego a la casa real de Hazael,",
            "y ese fuego destruirá los palacios de Ben-hadad."
          ],
          "rlw_lines": []
        },
        {
          "type": "verse",
          "verse_numbers": [
            5
          ],
          "lines": [
            "Abriré a la fuerza las puertas de Damasco;",
            "destruiré al que reina en Bicat-avén",
            "y al que gobierna en Bet-edén,",
            "y los sirios serán llevados cautivos a Quir.»",
            "Lo dice el Señor."
          ],
          "rlw_lines": []
        },
        {
          "type": "verse",
          "verse_numbers": [
            6
          ],
          "lines": [
            "Así dice el Señor:",
            "«Los de Gaza han cometido tantas maldades",
            "que no dejaré de castigarlos;",
            "pues se llevaron cautivo a todo un pueblo",
            "y lo vendieron en Edom como esclavo."
          ],
          "rlw_lines": []
        },
        {
          "type": "verse",
          "verse_numbers": [
            7
          ],
          "lines": [
            "Por eso pondré fuego a los muros de Gaza,",
            "y ese fuego destruirá sus palacios."
          ],
          "rlw_lines": []
        },
        {
          "type": "verse",
          "verse_numbers": [
            8
          ],
          "lines": [
            "Destruiré al que reina en Asdod",
            "y al que gobierna en Ascalón.",
            "¡Con todo mi poder me lanzaré contra Ecrón,",
            "y hasta el último filisteo morirá!»",
            "Lo dice el Señor."
          ],
          "rlw_lines": []
        },
        {
          "type": "verse",
          "verse_numbers": [
            9
          ],
          "lines": [
            "Así dice el Señor:",
            "«Los de Tiro han cometido tantas maldades",
            "que no dejaré de castigarlos;",
            "pues entregaron cautivo al poder de Edom",
            "a todo un pueblo con el que tenían una alianza de hermanos."
          ],
          "rlw_lines": []
        },
        {
          "type": "verse",
          "verse_numbers": [
            10
          ],
          "lines": [
            "Por eso pondré fuego a los muros de Tiro,",
            "y ese fuego destruirá sus palacios.»"
          ],
          "rlw_lines": []
        },
        {
          "type": "verse",
          "verse_numbers": [
            11
          ],
          "lines": [
            "Así dice el Señor:",
            "«Los de Edom han cometido tantas maldades",
            "que no dejaré de castigarlos;",
            "pues, espada en mano y sin compasión,",
            "persiguieron a sus hermanos israelitas.",
            "Dieron rienda suelta a su enojo,",
            "y su odio fue implacable."
          ],
          "rlw_lines": []
        },
        {
          "type": "verse",
          "verse_numbers": [
            12
          ],
          "lines": [
            "Por eso pondré fuego a Temán,",
            "y ese fuego destruirá los palacios de Bosrá.»,"
          ],
          "rlw_lines": []
        },
        {
          "type": "verse",
          "verse_numbers": [
            13
          ],
          "lines": [
            "Así dice el Señor:",
            "«Los de Amón han cometido tantas maldades",
            "que no dejaré de castigarlos;",
            "pues, en su afán de agrandar su territorio,",
            "abrieron en canal a las mujeres embarazadas de la región de Galaad."
          ],
          "rlw_lines": []
        },
        {
          "type": "verse",
          "verse_numbers": [
            14
          ],
          "lines": [
            "Por eso pondré fuego a los muros de Rabá,",
            "y ese fuego destruirá sus palacios",
            "entre clamores de batalla",
            "y estruendo de día tempestuoso."
          ],
          "rlw_lines": []
        },
        {
          "type": "verse",
          "verse_numbers": [
            15
          ],
          "lines": [
            "Y su rey marchará al destierro,",
            "junto con todos sus hombres importantes.»",
            "Lo dice el Señor."
          ],
          "rlw_lines": []
        }
      ]
    },
    {
      "chapter_usfm": "AMO.2",
      "is_chapter": true,
      "current": {
        "usfm": [
          "AMO.2"
        ],
        "human": "Amós 2"
      },
      "next": {
        "canonical": true,
        "usfm": [
          "AMO.3"
        ],
        "human": "Amós 3",
        "toc": true
      },
      "previous": {
        "canonical": true,
        "usfm": [
          "AMO.1"
        ],
        "human": "Amós 1",
        "toc": true
      },
      "items": [
        {
          "type": "verse",
          "verse_numbers": [
            1
          ],
          "lines": [
            "Así dice el Señor:",
            "«Los de Moab han cometido tantas maldades",
            "que no dejaré de castigarlos;",
            "pues quemaron los huesos del rey de Edom",
            "hasta convertirlos en ceniza."
          ],
          "rlw_lines": []
        },
        {
          "type": "verse",
          "verse_numbers": [
            2
          ],
          "lines": [
            "Por eso pondré fuego a la región de Moab,",
            "y ese fuego destruirá los palacios de Queriot;",
            "y entre clamores de batalla",
            "y toques de trompeta,",
            "los moabitas morirán."
          ],
          "rlw_lines": []
        },
        {
          "type": "verse",
          "verse_numbers": [
            3
          ],
          "lines": [
            "¡Quitaré al rey de en medio de su pueblo;",
            "lo mataré, y con él a sus hombres importantes!»",
            "Lo dice el Señor."
          ],
          "rlw_lines": []
        },
        {
          "type": "verse",
          "verse_numbers": [
            4
          ],
          "lines": [
            "Así dice el Señor:",
            "«Los de Judá han cometido tantas maldades",
            "que no dejaré de castigarlos;",
            "pues rechazaron las enseñanzas del Señor",
            "y no obedecieron sus leyes,",
            "sino que adoraron a los mismos ídolos",
            "que sus padres habían adorado."
          ],
          "rlw_lines": []
        },
        {
          "type": "verse",
          "verse_numbers": [
            5
          ],
          "lines": [
            "Por eso pondré fuego a Judá,",
            "y ese fuego destruirá los palacios de Jerusalén.»"
          ],
          "rlw_lines": []
        },
        {
          "type": "heading1",
          "verse_numbers": [],
          "lines": [
            "Juicio sobre Israel"
          ],
          "rlw_lines": []
        },
        {
          "type": "verse",
          "verse_numbers": [
            6
          ],
          "lines": [
            "Así dice el Señor:",
            "«Los de Israel han cometido tantas maldades",
            "que no dejaré de castigarlos;",
            "pues venden al inocente por dinero",
            "y al pobre por un par de sandalias."
          ],
          "rlw_lines": []
        },
        {
          "type": "verse",
          "verse_numbers": [
            7
          ],
          "lines": [
            "Oprimen y humillan a los pobres,",
            "y se niegan a hacer justicia a los humildes.",
            "El padre y el hijo se acuestan con la misma mujer,",
            "profanando así mi santo nombre."
          ],
          "rlw_lines": []
        },
        {
          "type": "verse",
          "verse_numbers": [
            8
          ],
          "lines": [
            "Tendidos sobre ropas que recibieron en prenda,",
            "participan en comidas en honor de los ídolos;",
            "con dinero de multas injustas compran vino,",
            "que beben en el templo de su dios."
          ],
          "rlw_lines": []
        },
        {
          "type": "verse",
          "verse_numbers": [
            9
          ],
          "lines": [
            "Yo, sin embargo, para abrirles paso a ustedes,",
            "destruí a los amorreos;",
            "los destruí por completo,",
            "aunque eran altos como cedros y fuertes como robles."
          ],
          "rlw_lines": []
        },
        {
          "type": "verse",
          "verse_numbers": [
            10
          ],
          "lines": [
            "Pero a ustedes los saqué de Egipto,",
            "y los conduje cuarenta años por el desierto",
            "para darles la tierra de ellos."
          ],
          "rlw_lines": []
        },
        {
          "type": "verse",
          "verse_numbers": [
            11
          ],
          "lines": [
            "Y no pueden negar, israelitas, que de entre ustedes",
            "a algunos los hice profetas y a otros nazareos.»",
            "El Señor lo afirma."
          ],
          "rlw_lines": []
        },
        {
          "type": "verse",
          "verse_numbers": [
            12
          ],
          "lines": [
            "«Pero ustedes obligaron a los nazareos a beber vino,",
            "y prohibieron a los profetas que hablaran en mi nombre."
          ],
          "rlw_lines": []
        },
        {
          "type": "verse",
          "verse_numbers": [
            13
          ],
          "lines": [
            "Pues bien, yo haré crujir la tierra",
            "bajo los pies de ustedes,",
            "como cruje una carreta cargada de trigo."
          ],
          "rlw_lines": []
        },
        {
          "type": "verse",
          "verse_numbers": [
            14
          ],
          "lines": [
            "Por mucho que corran, no escaparán;",
            "al más fuerte le faltarán las fuerzas,",
            "y no se salvará ni el más valiente."
          ],
          "rlw_lines": []
        },
        {
          "type": "verse",
          "verse_numbers": [
            15
          ],
          "lines": [
            "El arquero no resistirá, y no se salvarán",
            "ni el que corra con pies ligeros",
            "ni el que huya a caballo."
          ],
          "rlw_lines": []
        },
        {
          "type": "verse",
          "verse_numbers": [
            16
          ],
          "lines": [
            "Ese día, hasta el más valiente de los guerreros",
            "se despojará de sus armas para poder huir.»",
            "El Señor lo afirma."
          ],
          "rlw_lines": []
        }
      ]
    },
    {
      "chapter_usfm": "AMO.3",
      "is_chapter": true,
      "current": {
        "usfm": [
          "AMO.3"
        ],
        "human": "Amós 3"
      },
      "next": {
        "canonical": true,
        "usfm": [
          "AMO.4"
        ],
        "human": "Amós 4",
        "toc": true
      },
      "previous": {
        "canonical": true,
        "usfm": [
          "AMO.2"
        ],
        "human": "Amós 2",
        "toc": true
      },
      "items": [
        {
          "type": "heading2",
          "verse_numbers": [],
          "lines": [
            "III. DENUNCIAS Y AMENAZAS SOBRE ISRAEL"
          ],
          "rlw_lines": []
        },
        {
          "type": "section2",
          "verse_numbers": [],
          "lines": [
            "(3.1—6.14)"
          ],
          "rlw_lines": []
        },
        {
          "type": "heading1",
          "verse_numbers": [],
          "lines": [
            "La tarea del profeta"
          ],
          "rlw_lines": []
        },
        {
          "type": "verse",
          "verse_numbers": [
            1
          ],
          "lines": [
            "Israelitas, oigan lo que dice el Señor al pueblo que sacó de Egipto:"
          ],
          "rlw_lines": []
        },
        {
          "type": "verse",
          "verse_numbers": [
            2
          ],
          "lines": [
            "«Solo a ustedes he escogido",
            "de entre todos los pueblos de la tierra.",
            "Por eso habré de pedirles cuentas",
            "de todas las maldades que han cometido.»"
          ],
          "rlw_lines": []
        },
        {
          "type": "verse",
          "verse_numbers": [
            3
          ],
          "lines": [
            "Si dos caminan juntos, es porque están de acuerdo;"
          ],
          "rlw_lines": []
        },
        {
          "type": "verse",
          "verse_numbers": [
            4
          ],
          "lines": [
            "si el león ruge en la selva, es porque ha hecho una presa;",
            "si el cachorro gruñe en la cueva, es porque ha capturado algo;"
          ],
          "rlw_lines": []
        },
        {
          "type": "verse",
          "verse_numbers": [
            5
          ],
          "lines": [
            "si un pájaro cae al suelo, es porque había una trampa;",
            "si la trampa salta del suelo, es porque algo ha atrapado;"
          ],
          "rlw_lines": []
        },
        {
          "type": "verse",
          "verse_numbers": [
            6
          ],
          "lines": [
            "si la trompeta suena en la ciudad, la gente se alarma;",
            "si algo malo pasa en la ciudad, es porque el Señor lo ha mandado."
          ],
          "rlw_lines": []
        },
        {
          "type": "verse",
          "verse_numbers": [
            7
          ],
          "lines": [
            "Nunca hace nada el Señor",
            "sin revelarlo a sus siervos los profetas."
          ],
          "rlw_lines": []
        },
        {
          "type": "verse",
          "verse_numbers": [
            8
          ],
          "lines": [
            "¿Quién no tiembla de miedo, si el león ruge?",
            "¿Quién no habla en nombre del Señor, si él lo ordena?"
          ],
          "rlw_lines": []
        },
        {
          "type": "heading1",
          "verse_numbers": [],
          "lines": [
            "Destrucción de Samaria"
          ],
          "rlw_lines": []
        },
        {
          "type": "verse",
          "verse_numbers": [
            9
          ],
          "lines": [
            "Proclamen ustedes en los palacios de Asdod",
            "y en los palacios de Egipto:",
            "«Vengan a los montes de Samaria;",
            "vean los desórdenes que hay en ella",
            "y la violencia que allí se sufre.»"
          ],
          "rlw_lines": []
        },
        {
          "type": "verse",
          "verse_numbers": [
            10
          ],
          "lines": [
            "El Señor afirma:",
            "«Ellos no saben actuar con rectitud;",
            "guardan en sus palacios lo que robaron con violencia.»"
          ],
          "rlw_lines": []
        },
        {
          "type": "verse",
          "verse_numbers": [
            11
          ],
          "lines": [
            "Por tanto, así dice Dios el Señor:",
            "«Un enemigo rodeará el país,",
            "derribará tu fortaleza",
            "y saqueará tus palacios.»"
          ],
          "rlw_lines": []
        },
        {
          "type": "verse",
          "verse_numbers": [
            12
          ],
          "lines": [
            "Así dice el Señor:",
            "«Como el pastor salva de la boca del león",
            "dos patas o la punta de una oreja,",
            "así escaparán los israelitas",
            "que viven en Samaria,",
            "esos que se recuestan en lujosos divanes de Damasco.»"
          ],
          "rlw_lines": []
        },
        {
          "type": "verse",
          "verse_numbers": [
            13
          ],
          "lines": [
            "El Señor, el Dios todopoderoso, afirma:",
            "«Oigan ustedes y den testimonio contra el pueblo de Jacob,"
          ],
          "rlw_lines": []
        },
        {
          "type": "verse",
          "verse_numbers": [
            14
          ],
          "lines": [
            "pues el día en que yo pida cuentas a Israel por sus pecados,",
            "destruiré los altares de Betel;",
            "los cuernos del altar serán cortados",
            "y caerán a tierra."
          ],
          "rlw_lines": []
        },
        {
          "type": "verse",
          "verse_numbers": [
            15
          ],
          "lines": [
            "Destruiré las casas de invierno y de verano,",
            "pondré fin a las casas de marfil",
            "y arruinaré los grandes palacios.»",
            "El Señor lo afirma."
          ],
          "rlw_lines": []
        }
      ]
    },
    {
      "chapter_usfm": "AMO.4",
      "is_chapter": true,
      "current": {
        "usfm": [
          "AMO.4"
        ],
        "human": "Amós 4"
      },
      "next": {
        "canonical": true,
        "usfm": [
          "AMO.5"
        ],
        "human": "Amós 5",
        "toc": true
      },
      "previous": {
        "canonical": true,
        "usfm": [
          "AMO.3"
        ],
        "human": "Amós 3",
        "toc": true
      },
      "items": [
        {
          "type": "verse",
          "verse_numbers": [
            1
          ],
          "lines": [
            "Escuchen esto, vacas de Basán,",
            "damas de Samaria,",
            "que oprimen a los pobres",
            "y maltratan a los necesitados,",
            "que ordenan a sus maridos",
            "traerles vino para beber."
          ],
          "rlw_lines": []
        },
        {
          "type": "verse",
          "verse_numbers": [
            2
          ],
          "lines": [
            "Dios el Señor juró por su santidad:",
            "«Vienen días en que a ustedes",
            "se las llevarán con ganchos,",
            "y sus hijos serán enganchados con anzuelos."
          ],
          "rlw_lines": []
        },
        {
          "type": "verse",
          "verse_numbers": [
            3
          ],
          "lines": [
            "Tendrán que salir por las brechas, en fila,",
            "y las echarán al monte Hermón.»",
            "El Señor lo afirma."
          ],
          "rlw_lines": []
        },
        {
          "type": "heading1",
          "verse_numbers": [],
          "lines": [
            "Una exhortación irónica"
          ],
          "rlw_lines": []
        },
        {
          "type": "verse",
          "verse_numbers": [
            4
          ],
          "lines": [
            "«Vayan a Betel, y a Guilgal;",
            "¡pequen, aumenten sus rebeliones!",
            "Lleven sus sacrificios por la mañana",
            "y sus diezmos cada tercer día."
          ],
          "rlw_lines": []
        },
        {
          "type": "verse",
          "verse_numbers": [
            5
          ],
          "lines": [
            "Quemen panes sin levadura en ofrenda de gratitud,",
            "y anuncien por todas partes sus ofrendas voluntarias,",
            "ya que eso es lo que a ustedes les encanta.»",
            "El Señor lo afirma."
          ],
          "rlw_lines": []
        },
        {
          "type": "heading1",
          "verse_numbers": [],
          "lines": [
            "A pesar del castigo, Israel no aprende"
          ],
          "rlw_lines": []
        },
        {
          "type": "verse",
          "verse_numbers": [
            6
          ],
          "lines": [
            "«Yo hice que ustedes pasaran hambre",
            "en todas sus ciudades;",
            "yo hice que les faltara comida",
            "en todos sus poblados,",
            "¡pero ustedes no se volvieron a mí!»",
            "El Señor lo afirma."
          ],
          "rlw_lines": []
        },
        {
          "type": "verse",
          "verse_numbers": [
            7
          ],
          "lines": [
            "«También hice que les faltara la lluvia",
            "durante tres meses antes de la cosecha.",
            "En una ciudad hice llover y en otra no;",
            "en un campo llovió y otro se secó por falta de agua;"
          ],
          "rlw_lines": []
        },
        {
          "type": "verse",
          "verse_numbers": [
            8
          ],
          "lines": [
            "de ciudad en ciudad iba la gente en busca de agua,",
            "y no encontraban bastante para calmar su sed,",
            "¡pero ustedes no se volvieron a mí!»",
            "El Señor lo afirma."
          ],
          "rlw_lines": []
        },
        {
          "type": "verse",
          "verse_numbers": [
            9
          ],
          "lines": [
            "«Los azoté con vientos calurosos y con plagas,",
            "hice que se marchitaran sus huertos y sus viñedos,",
            "la langosta se comió sus higueras y sus olivos,",
            "¡pero ustedes no se volvieron a mí!»",
            "El Señor lo afirma."
          ],
          "rlw_lines": []
        },
        {
          "type": "verse",
          "verse_numbers": [
            10
          ],
          "lines": [
            "«Les mandé una plaga como las que mandé sobre Egipto;",
            "hice que sus jóvenes murieran en los campos de batalla",
            "y dejé que el enemigo se adueñara de sus caballos;",
            "les hice oler la peste de los muertos en los campamentos,",
            "¡pero ustedes no se volvieron a mí!»",
            "El Señor lo afirma."
          ],
          "rlw_lines": []
        },
        {
          "type": "verse",
          "verse_numbers": [
            11
          ],
          "lines": [
            "«Los destruí con una catástrofe",
            "como la que mandé sobre Sodoma y Gomorra;",
            "parecían una brasa sacada del fuego,",
            "¡pero ustedes no se volvieron a mí!»",
            "El Señor lo afirma."
          ],
          "rlw_lines": []
        },
        {
          "type": "verse",
          "verse_numbers": [
            12
          ],
          "lines": [
            "«Por eso, Israel, voy a hacer lo mismo contigo;",
            "y porque voy a hacerlo,",
            "¡prepárate para encontrarte con tu Dios!»"
          ],
          "rlw_lines": []
        },
        {
          "type": "verse",
          "verse_numbers": [
            13
          ],
          "lines": [
            "El Señor, el que forma las montañas y crea el viento,",
            "el que da a conocer sus planes al hombre,",
            "el que convierte la luz en oscuridad,",
            "el que recorre las regiones más altas de la tierra,",
            "el Señor, el Dios todopoderoso: ese es su nombre."
          ],
          "rlw_lines": []
        }
      ]
    },
    {
      "chapter_usfm": "AMO.5",
      "is_chapter": true,
      "current": {
        "usfm": [
          "AMO.5"
        ],
        "human": "Amós 5"
      },
      "next": {
        "canonical": true,
        "usfm": [
          "AMO.6"
        ],
        "human": "Amós 6",
        "toc": true
      },
      "previous": {
        "canonical": true,
        "usfm": [
          "AMO.4"
        ],
        "human": "Amós 4",
        "toc": true
      },
      "items": [
        {
          "type": "heading1",
          "verse_numbers": [],
          "lines": [
            "Llamado a volverse a Dios"
          ],
          "rlw_lines": []
        },
        {
          "type": "verse",
          "verse_numbers": [
            1
          ],
          "lines": [
            "Oigan mis palabras, israelitas;",
            "escuchen el lamento que entono contra ustedes:"
          ],
          "rlw_lines": []
        },
        {
          "type": "verse",
          "verse_numbers": [
            2
          ],
          "lines": [
            "La bella y pura Israel ha caído;",
            "cayó para no levantarse más.",
            "Quedó tendida sobre su propio suelo,",
            "y no hay quien la levante."
          ],
          "rlw_lines": []
        },
        {
          "type": "verse",
          "verse_numbers": [
            3
          ],
          "lines": [
            "Así dice Dios el Señor a los israelitas:",
            "«Si una ciudad manda mil hombres a la guerra,",
            "solo cien volverán con vida;",
            "y si una ciudad manda cien,",
            "solo diez regresarán.»"
          ],
          "rlw_lines": []
        },
        {
          "type": "verse",
          "verse_numbers": [
            4
          ],
          "lines": [
            "Así dice el Señor a los israelitas:",
            "«Acudan a mí, y vivirán."
          ],
          "rlw_lines": []
        },
        {
          "type": "verse",
          "verse_numbers": [
            5
          ],
          "lines": [
            "No acudan a Betel,",
            "no vayan a Guilgal",
            "ni pasen por Beerseba,",
            "porque Guilgal irá sin remedio al destierro",
            "y Betel quedará convertida en ruinas.»"
          ],
          "rlw_lines": []
        },
        {
          "type": "verse",
          "verse_numbers": [
            6
          ],
          "lines": [
            "Acudan al Señor, y vivirán;",
            "de otro modo él enviará fuego sobre el reino de Israel,",
            "y no habrá en Betel quien lo apague."
          ],
          "rlw_lines": []
        },
        {
          "type": "verse",
          "verse_numbers": [
            7
          ],
          "lines": [
            "¡Ay de ustedes, que convierten la justicia en amargura",
            "y arrojan por los suelos el derecho!"
          ],
          "rlw_lines": []
        },
        {
          "type": "verse",
          "verse_numbers": [
            8,
            9
          ],
          "lines": [
            "El Señor, que hizo las Pléyades y el Orión,",
            "es quien convierte la noche en día",
            "y el día en noche oscura;",
            "quien llama a las aguas del mar",
            "y las derrama sobre la tierra;",
            "quien desencadena la ruina sobre la fortaleza",
            "y la hace llegar sobre la fortificación.",
            "El Señor, ese es su nombre."
          ],
          "rlw_lines": []
        },
        {
          "type": "verse",
          "verse_numbers": [
            10
          ],
          "lines": [
            "¡Ay de ustedes, que odian al defensor de la justicia",
            "y detestan al testigo honrado!"
          ],
          "rlw_lines": []
        },
        {
          "type": "verse",
          "verse_numbers": [
            11
          ],
          "lines": [
            "Puesto que pisotean al pobre",
            "y le cobran impuestos de trigo,",
            "no podrán vivir en las casas de piedra que han construido,",
            "ni beberán el vino de los viñedos que han plantado."
          ],
          "rlw_lines": []
        },
        {
          "type": "verse",
          "verse_numbers": [
            12
          ],
          "lines": [
            "Yo conozco sus muchas maldades",
            "y sus pecados sin fin:",
            "oprimen al justo, reciben soborno",
            "y en los tribunales hacen que el pobre pierda su causa."
          ],
          "rlw_lines": []
        },
        {
          "type": "verse",
          "verse_numbers": [
            13
          ],
          "lines": [
            "Por eso el que es sabio se calla,",
            "porque el tiempo es malo."
          ],
          "rlw_lines": []
        },
        {
          "type": "verse",
          "verse_numbers": [
            14
          ],
          "lines": [
            "Busquen el bien y no el mal, y vivirán;",
            "así será verdad lo que ustedes dicen:",
            "que el Señor, el Dios todopoderoso, está con ustedes."
          ],
          "rlw_lines": []
        },
        {
          "type": "verse",
          "verse_numbers": [
            15
          ],
          "lines": [
            "¡Odien el mal! ¡Amen el bien!",
            "Asegúrense de que en los tribunales se haga justicia;",
            "quizá entonces el Señor, el Dios todopoderoso,",
            "tendrá piedad de los sobrevivientes de Israel."
          ],
          "rlw_lines": []
        },
        {
          "type": "verse",
          "verse_numbers": [
            16
          ],
          "lines": [
            "Así dice el Señor, el Dios todopoderoso:",
            "«En todas las plazas habrá llanto,",
            "en todas las calles habrá gritos de dolor.",
            "Llamarán al duelo a los campesinos,",
            "y a los llorones profesionales al llanto."
          ],
          "rlw_lines": []
        },
        {
          "type": "verse",
          "verse_numbers": [
            17
          ],
          "lines": [
            "En todos los viñedos llorarán",
            "cuando yo venga a castigarlos.»",
            "Lo dice el Señor."
          ],
          "rlw_lines": []
        },
        {
          "type": "verse",
          "verse_numbers": [
            18
          ],
          "lines": [
            "¡Ay de los que ansían que llegue el día del Señor!",
            "¿Saben cómo va a ser para ustedes ese día?",
            "Será día de oscuridad, y no de luz."
          ],
          "rlw_lines": []
        },
        {
          "type": "verse",
          "verse_numbers": [
            19
          ],
          "lines": [
            "Será como cuando uno huye de un león",
            "y se topa con un oso,",
            "o como cuando uno entra en su casa,",
            "se apoya en la pared,",
            "y lo muerde una culebra."
          ],
          "rlw_lines": []
        },
        {
          "type": "verse",
          "verse_numbers": [
            20
          ],
          "lines": [
            "Sí, el día del Señor será de oscuridad, y no de luz;",
            "de densa oscuridad, sin claridad ninguna."
          ],
          "rlw_lines": []
        },
        {
          "type": "verse",
          "verse_numbers": [
            21
          ],
          "lines": [
            "«Odio y desprecio las fiestas religiosas que ustedes celebran;",
            "me disgustan sus reuniones solemnes."
          ],
          "rlw_lines": []
        },
        {
          "type": "verse",
          "verse_numbers": [
            22
          ],
          "lines": [
            "No quiero los holocaustos que ofrecen en mi honor,",
            "ni sus ofrendas de cereales;",
            "no aceptaré los gordos becerros",
            "de sus sacrificios de reconciliación."
          ],
          "rlw_lines": []
        },
        {
          "type": "verse",
          "verse_numbers": [
            23
          ],
          "lines": [
            "¡Alejen de mí el ruido de sus cantos!",
            "¡No quiero oír el sonido de sus arpas!"
          ],
          "rlw_lines": []
        },
        {
          "type": "verse",
          "verse_numbers": [
            24
          ],
          "lines": [
            "Pero que fluya como agua la justicia,",
            "y la honradez como un manantial inagotable."
          ],
          "rlw_lines": []
        },
        {
          "type": "verse",
          "verse_numbers": [
            25
          ],
          "lines": [
            "»Israelitas, ¿acaso en los cuarenta años del desierto me ofrecieron ustedes sacrificios y ofrendas?"
          ],
          "rlw_lines": []
        },
        {
          "type": "verse",
          "verse_numbers": [
            26
          ],
          "lines": [
            "Ahora, sin embargo, tendrán que cargar con su rey Sicut y su estrella Quiiún, imágenes de dioses que ustedes mismos se han hecho."
          ],
          "rlw_lines": []
        },
        {
          "type": "verse",
          "verse_numbers": [
            27
          ],
          "lines": [
            "Los lanzaré a ustedes al destierro, más allá de Damasco.», Lo dice el Señor, el Dios todopoderoso. Ese es su nombre."
          ],
          "rlw_lines": []
        }
      ]
    },
    {
      "chapter_usfm": "AMO.6",
      "is_chapter": true,
      "current": {
        "usfm": [
          "AMO.6"
        ],
        "human": "Amós 6"
      },
      "next": {
        "canonical": true,
        "usfm": [
          "AMO.7"
        ],
        "human": "Amós 7",
        "toc": true
      },
      "previous": {
        "canonical": true,
        "usfm": [
          "AMO.5"
        ],
        "human": "Amós 5",
        "toc": true
      },
      "items": [
        {
          "type": "heading1",
          "verse_numbers": [],
          "lines": [
            "Destrucción de Israel"
          ],
          "rlw_lines": []
        },
        {
          "type": "verse",
          "verse_numbers": [
            1
          ],
          "lines": [
            "»¡Ay de los que llevan una vida fácil en Sión!",
            "¡Ay de los que viven confiados en Samaria,",
            "los jefes de la nación más importante,",
            "a quienes recurren los israelitas!"
          ],
          "rlw_lines": []
        },
        {
          "type": "verse",
          "verse_numbers": [
            2
          ],
          "lines": [
            "Vayan a Calné, y vean;",
            "de allí pasen a Hamat la grande,",
            "y bajen a Gat de los filisteos.",
            "¿Son acaso ustedes mejores que esos países?",
            "¿Es el país de ustedes mejor que el de ellos?"
          ],
          "rlw_lines": []
        },
        {
          "type": "verse",
          "verse_numbers": [
            3
          ],
          "lines": [
            "Ustedes no quieren pensar en el día malo,",
            "pero están atrayendo el imperio de la violencia."
          ],
          "rlw_lines": []
        },
        {
          "type": "verse",
          "verse_numbers": [
            4
          ],
          "lines": [
            "Recostados en lujosos divanes de marfil,",
            "se tienden a sus anchas en sus fiestas;",
            "banquetean con corderitos y gordos becerros;"
          ],
          "rlw_lines": []
        },
        {
          "type": "verse",
          "verse_numbers": [
            5
          ],
          "lines": [
            "tocan la flauta sin ton ni son;",
            "imitan a David, inventando instrumentos musicales;"
          ],
          "rlw_lines": []
        },
        {
          "type": "verse",
          "verse_numbers": [
            6
          ],
          "lines": [
            "beben vino en grandes copas,",
            "usan los más finos perfumes,",
            "¡y nada les importa la ruina del país!"
          ],
          "rlw_lines": []
        },
        {
          "type": "verse",
          "verse_numbers": [
            7
          ],
          "lines": [
            "Ustedes serán los primeros en ir al destierro,",
            "y se acabará el alboroto de sus banquetes.»"
          ],
          "rlw_lines": []
        },
        {
          "type": "verse",
          "verse_numbers": [
            8
          ],
          "lines": [
            "El Señor ha jurado por sí mismo; el Señor, el Dios todopoderoso, lo afirma:",
            "«Odio el orgullo del pueblo de Jacob;",
            "aborrezco sus palacios;",
            "entregaré la ciudad al enemigo,",
            "junto con todo lo que hay en ella.»"
          ],
          "rlw_lines": []
        },
        {
          "type": "verse",
          "verse_numbers": [
            9
          ],
          "lines": [
            "Entonces, si quedan diez hombres en una casa, los diez morirán."
          ],
          "rlw_lines": []
        },
        {
          "type": "verse",
          "verse_numbers": [
            10
          ],
          "lines": [
            "Tan grande será el terror que, cuando alguien levante el cadáver de un pariente para sacarlo de la casa, le dirá a otro pariente que ande adentro: «¿Hay alguien más contigo?» «No», responderá el otro. Y dirá el primero: «¡Cállate, no sea que pronuncies el nombre del Señor!»"
          ],
          "rlw_lines": []
        },
        {
          "type": "verse",
          "verse_numbers": [
            11
          ],
          "lines": [
            "Porque el Señor va a ordenar su castigo sobre las casas grandes y sobre las pequeñas, y todas quedarán completamente en ruinas."
          ],
          "rlw_lines": []
        },
        {
          "type": "verse",
          "verse_numbers": [
            12
          ],
          "lines": [
            "¿Pueden los caballos trepar por las peñas?",
            "¿Acaso se puede arar en el mar?",
            "¡Pues ustedes han convertido la justicia en veneno",
            "y el fruto de la justicia en amargura!"
          ],
          "rlw_lines": []
        },
        {
          "type": "verse",
          "verse_numbers": [
            13
          ],
          "lines": [
            "Ustedes se alegran falsamente, y dicen:",
            "«Con nuestra propia fuerza hemos adquirido poder.»"
          ],
          "rlw_lines": []
        },
        {
          "type": "verse",
          "verse_numbers": [
            14
          ],
          "lines": [
            "Pues fíjense bien, israelitas;",
            "el Señor, el Dios todopoderoso, afirma:",
            "«Yo levantaré contra ustedes una nación",
            "que los oprimirá por completo,",
            "desde el extremo norte hasta el extremo sur.»"
          ],
          "rlw_lines": []
        }
      ]
    },
    {
      "chapter_usfm": "AMO.7",
      "is_chapter": true,
      "current": {
        "usfm": [
          "AMO.7"
        ],
        "human": "Amós 7"
      },
      "next": {
        "canonical": true,
        "usfm": [
          "AMO.8"
        ],
        "human": "Amós 8",
        "toc": true
      },
      "previous": {
        "canonical": true,
        "usfm": [
          "AMO.6"
        ],
        "human": "Amós 6",
        "toc": true
      },
      "items": [
        {
          "type": "heading2",
          "verse_numbers": [],
          "lines": [
            "IV. CINCO VISIONES PROFÉTICAS"
          ],
          "rlw_lines": []
        },
        {
          "type": "section2",
          "verse_numbers": [],
          "lines": [
            "(7.1—9.10)"
          ],
          "rlw_lines": []
        },
        {
          "type": "heading1",
          "verse_numbers": [],
          "lines": [
            "Visión de las langostas"
          ],
          "rlw_lines": []
        },
        {
          "type": "verse",
          "verse_numbers": [
            1
          ],
          "lines": [
            "Esto me mostró el Señor: Cuando apenas comenzaba a brotar la siembra tardía, la que se hace después de la cosecha del rey, vi al Señor creando langostas."
          ],
          "rlw_lines": []
        },
        {
          "type": "verse",
          "verse_numbers": [
            2
          ],
          "lines": [
            "Y cuando las langostas ya estaban comiéndose hasta la última hierba, dije:",
            "—¡Señor, perdónanos! ¿Cómo va a resistir tu pueblo Jacob, si es tan pequeño?"
          ],
          "rlw_lines": []
        },
        {
          "type": "verse",
          "verse_numbers": [
            3
          ],
          "lines": [
            "Entonces el Señor desistió de su propósito, y dijo:",
            "—¡Eso no va a suceder!"
          ],
          "rlw_lines": []
        },
        {
          "type": "heading1",
          "verse_numbers": [],
          "lines": [
            "Visión del fuego"
          ],
          "rlw_lines": []
        },
        {
          "type": "verse",
          "verse_numbers": [
            4
          ],
          "lines": [
            "Esto me mostró el Señor: Le vi enviar como castigo un fuego abrasador, que secó por completo el gran mar profundo y que estaba acabando también con los campos."
          ],
          "rlw_lines": []
        },
        {
          "type": "verse",
          "verse_numbers": [
            5
          ],
          "lines": [
            "Yo dije:",
            "—¡Deténte, Señor, por favor! ¿Cómo va a resistir tu pueblo Jacob, si es tan pequeño?"
          ],
          "rlw_lines": []
        },
        {
          "type": "verse",
          "verse_numbers": [
            6
          ],
          "lines": [
            "Entonces el Señor desistió de su propósito, y dijo:",
            "—¡Tampoco esto va a suceder!"
          ],
          "rlw_lines": []
        },
        {
          "type": "heading1",
          "verse_numbers": [],
          "lines": [
            "Visión de la plomada"
          ],
          "rlw_lines": []
        },
        {
          "type": "verse",
          "verse_numbers": [
            7
          ],
          "lines": [
            "El Señor me mostró también esto: Estaba él junto a un muro, y tenía en la mano una plomada de albañil."
          ],
          "rlw_lines": []
        },
        {
          "type": "verse",
          "verse_numbers": [
            8
          ],
          "lines": [
            "Y me preguntó:",
            "—¿Qué ves, Amós?",
            "—Una plomada de albañil —respondí.",
            "Entonces me dijo:",
            "—Pues con esta plomada de albañil voy a ver cómo es de recta la conducta de mi pueblo Israel. No le voy a perdonar ni una vez más."
          ],
          "rlw_lines": []
        },
        {
          "type": "verse",
          "verse_numbers": [
            9
          ],
          "lines": [
            "Los santuarios de Isaac serán destruidos, y los templos de Israel quedarán en ruinas. ¡Alzaré la espada contra la familia de Jeroboam!"
          ],
          "rlw_lines": []
        },
        {
          "type": "heading1",
          "verse_numbers": [],
          "lines": [
            "Amós se enfrenta a Amasías"
          ],
          "rlw_lines": []
        },
        {
          "type": "verse",
          "verse_numbers": [
            10
          ],
          "lines": [
            "Amasías, sacerdote de Betel, mandó decir a Jeroboam, rey de Israel: «Amós anda entre la gente de Israel, conspirando contra Su Majestad. El país ya no puede soportar que siga hablando."
          ],
          "rlw_lines": []
        },
        {
          "type": "verse",
          "verse_numbers": [
            11
          ],
          "lines": [
            "Porque anda por ahí diciendo: “Jeroboam morirá a filo de espada, y todo el pueblo de Israel será llevado al destierro.”»"
          ],
          "rlw_lines": []
        },
        {
          "type": "verse",
          "verse_numbers": [
            12
          ],
          "lines": [
            "Luego, Amasías le ordenó a Amós:",
            "—¡Largo de aquí, profeta! Si quieres ganarte la vida profetizando, vete a Judá;"
          ],
          "rlw_lines": []
        },
        {
          "type": "verse",
          "verse_numbers": [
            13
          ],
          "lines": [
            "pero no profetices más en Betel, porque es santuario del rey y templo principal del reino."
          ],
          "rlw_lines": []
        },
        {
          "type": "verse",
          "verse_numbers": [
            14
          ],
          "lines": [
            "Pero Amós le contestó:",
            "—Yo no soy profeta, ni pretendo serlo. Me gano la vida cuidando ovejas y recogiendo higos silvestres,"
          ],
          "rlw_lines": []
        },
        {
          "type": "verse",
          "verse_numbers": [
            15
          ],
          "lines": [
            "pero el Señor me quitó de andar cuidando ovejas, y me dijo: “Ve y habla en mi nombre a mi pueblo Israel.”"
          ],
          "rlw_lines": []
        },
        {
          "type": "verse",
          "verse_numbers": [
            16
          ],
          "lines": [
            "Por lo tanto, oye la palabra del Señor. Esto es lo que tú dices: “No hables nada en nombre de Dios contra Israel, ni digas nada contra los descendientes de Isaac.”"
          ],
          "rlw_lines": []
        },
        {
          "type": "verse",
          "verse_numbers": [
            17
          ],
          "lines": [
            "Pero esto es lo que dice el Señor: “Tu mujer se prostituirá en plena ciudad, y tus hijos e hijas morirán a filo de espada; tus tierras serán repartidas en sorteo; tú mismo morirás en tierra de paganos, y los israelitas serán llevados cautivos, lejos de su tierra.”"
          ],
          "rlw_lines": []
        }
      ]
    },
    {
      "chapter_usfm": "AMO.8",
      "is_chapter": true,
      "current": {
        "usfm": [
          "AMO.8"
        ],
        "human": "Amós 8"
      },
      "next": {
        "canonical": true,
        "usfm": [
          "AMO.9"
        ],
        "human": "Amós 9",
        "toc": true
      },
      "previous": {
        "canonical": true,
        "usfm": [
          "AMO.7"
        ],
        "human": "Amós 7",
        "toc": true
      },
      "items": [
        {
          "type": "heading1",
          "verse_numbers": [],
          "lines": [
            "La cesta de fruta madura"
          ],
          "rlw_lines": []
        },
        {
          "type": "verse",
          "verse_numbers": [
            1
          ],
          "lines": [
            "Esto me mostró Dios el Señor: Había una cesta de fruta madura,"
          ],
          "rlw_lines": []
        },
        {
          "type": "verse",
          "verse_numbers": [
            2
          ],
          "lines": [
            "y él me preguntó:",
            "—¿Qué ves, Amós?",
            "—Una cesta de fruta madura —respondí.",
            "Y me dijo el Señor:",
            "—Ya Israel está maduro; no le voy a perdonar ni una vez más."
          ],
          "rlw_lines": []
        },
        {
          "type": "verse",
          "verse_numbers": [
            3
          ],
          "lines": [
            "Ese día los cantos del palacio se volverán lamentos. Mucha gente morirá, y en silencio serán arrojados fuera sus cadáveres. El Señor lo afirma."
          ],
          "rlw_lines": []
        },
        {
          "type": "heading1",
          "verse_numbers": [],
          "lines": [
            "Se acerca el juicio de Israel"
          ],
          "rlw_lines": []
        },
        {
          "type": "verse",
          "verse_numbers": [
            4
          ],
          "lines": [
            "Oigan esto, ustedes que oprimen a los humildes y arruinan a los pobres del país;"
          ],
          "rlw_lines": []
        },
        {
          "type": "verse",
          "verse_numbers": [
            5
          ],
          "lines": [
            "ustedes que dicen: «¿Cuándo pasará la fiesta de la luna nueva, para que podamos vender el trigo? ¿Cuándo pasará el sábado, para que vendamos el grano a precios altos y usando medidas con trampa y pesas falsas?"
          ],
          "rlw_lines": []
        },
        {
          "type": "verse",
          "verse_numbers": [
            6
          ],
          "lines": [
            "¡Arruinaremos a los pobres hasta que ellos mismos se nos vendan como esclavos para pagar sus deudas, aunque solo deban un par de sandalias! ¡Venderemos hasta el desecho del trigo!»"
          ],
          "rlw_lines": []
        },
        {
          "type": "verse",
          "verse_numbers": [
            7
          ],
          "lines": [
            "El Señor ha jurado por la gloria de Jacob: «Nunca olvidaré lo que han hecho.»"
          ],
          "rlw_lines": []
        },
        {
          "type": "verse",
          "verse_numbers": [
            8
          ],
          "lines": [
            "¿Y no habrá de temblar la tierra por todo esto?",
            "¿No habrán de llorar todos sus habitantes?",
            "¡La tierra subirá y bajará,",
            "como suben y bajan las aguas del Nilo!"
          ],
          "rlw_lines": []
        },
        {
          "type": "verse",
          "verse_numbers": [
            9
          ],
          "lines": [
            "«Ese día —afirma el Señor—,",
            "haré que se oculte el sol al mediodía,",
            "y en pleno día cubriré de oscuridad la tierra."
          ],
          "rlw_lines": []
        },
        {
          "type": "verse",
          "verse_numbers": [
            10
          ],
          "lines": [
            "Cambiaré las fiestas en llanto por los muertos,",
            "y los cantos en lamentos fúnebres;",
            "haré que ustedes se vistan de luto,",
            "y que se rapen la cabeza en señal de dolor.",
            "Llorarán como el que ha perdido a su único hijo,",
            "y todo acabará en amargura."
          ],
          "rlw_lines": []
        },
        {
          "type": "verse",
          "verse_numbers": [
            11
          ],
          "lines": [
            "Vienen días —afirma el Señor—",
            "en los cuales mandaré hambre a la tierra;",
            "no hambre de pan, ni sed de agua,",
            "sino hambre de oír la palabra del Señor."
          ],
          "rlw_lines": []
        },
        {
          "type": "verse",
          "verse_numbers": [
            12
          ],
          "lines": [
            "La gente andará errante,",
            "buscando la palabra del Señor;",
            "irán de un mar al otro mar,",
            "y desde el norte y hasta el oriente,",
            "pero no podrán encontrarla."
          ],
          "rlw_lines": []
        },
        {
          "type": "verse",
          "verse_numbers": [
            13
          ],
          "lines": [
            "Hermosas muchachas y valientes muchachos",
            "se desmayarán de sed ese día."
          ],
          "rlw_lines": []
        },
        {
          "type": "verse",
          "verse_numbers": [
            14
          ],
          "lines": [
            "Los que juran por los ídolos de Samaria;",
            "los que dicen: “Por vida de tu dios, oh Dan”,",
            "“Por vida de los dioses de Beerseba”,",
            "caerán para no levantarse más.»"
          ],
          "rlw_lines": []
        }
      ]
    },
    {
      "chapter_usfm": "AMO.9",
      "is_chapter": true,
      "current": {
        "usfm": [
          "AMO.9"
        ],
        "human": "Amós 9"
      },
      "next": {
        "canonical": true,
        "usfm": [
          "OBA.1"
        ],
        "human": "Abdías 1",
        "toc": true
      },
      "previous": {
        "canonical": true,
        "usfm": [
          "AMO.8"
        ],
        "human": "Amós 8",
        "toc": true
      },
      "items": [
        {
          "type": "heading1",
          "verse_numbers": [],
          "lines": [
            "Nadie escapa al juicio del Señor"
          ],
          "rlw_lines": []
        },
        {
          "type": "verse",
          "verse_numbers": [
            1
          ],
          "lines": [
            "Vi al Señor, que estaba junto al altar y me decía:",
            "«Golpea los capiteles hasta que tiemblen los umbrales;",
            "¡que caigan hechos pedazos sobre la gente!",
            "A quienes queden vivos, los mataré a filo de espada:",
            "aunque traten de huir, ni uno solo se salvará;"
          ],
          "rlw_lines": []
        },
        {
          "type": "verse",
          "verse_numbers": [
            2
          ],
          "lines": [
            "aunque se escondan en las profundidades de la tierra,",
            "de allí los sacaré;",
            "aunque suban a las alturas de los cielos,",
            "de allí los haré bajar."
          ],
          "rlw_lines": []
        },
        {
          "type": "verse",
          "verse_numbers": [
            3
          ],
          "lines": [
            "Si se esconden en la cumbre del monte Carmelo,",
            "aun allá los iré a buscar;",
            "si se esconden de mí en el fondo del mar,",
            "mandaré al monstruo marino que vaya y los destroce;"
          ],
          "rlw_lines": []
        },
        {
          "type": "verse",
          "verse_numbers": [
            4
          ],
          "lines": [
            "y si van al destierro, llevados por sus enemigos,",
            "mandaré a la espada que vaya y los mate.",
            "¡Para mal, y no para bien,",
            "los tendré siempre a la vista!»"
          ],
          "rlw_lines": []
        },
        {
          "type": "verse",
          "verse_numbers": [
            5
          ],
          "lines": [
            "El Señor, el Dios todopoderoso,",
            "toca la tierra, y la tierra se derrite",
            "y lloran todos sus habitantes.",
            "La tierra sube y baja,",
            "como suben y bajan las aguas del Nilo."
          ],
          "rlw_lines": []
        },
        {
          "type": "verse",
          "verse_numbers": [
            6
          ],
          "lines": [
            "El Señor ha puesto su habitación en el cielo",
            "y la bóveda celeste sobre la tierra;",
            "él llama a las aguas del mar",
            "y las derrama sobre la tierra.",
            "El Señor, ese es su nombre."
          ],
          "rlw_lines": []
        },
        {
          "type": "verse",
          "verse_numbers": [
            7
          ],
          "lines": [
            "Esto afirma el Señor:",
            "«Israelitas, para mí no hay diferencia",
            "entre ustedes y los etiopes.",
            "Así como los traje a ustedes de Egipto,",
            "así traje también de Creta a los filisteos",
            "y de Quir a los arameos.»"
          ],
          "rlw_lines": []
        },
        {
          "type": "verse",
          "verse_numbers": [
            8
          ],
          "lines": [
            "El Señor mira este reino pecador, y dice:",
            "«Lo voy a borrar de la tierra,",
            "pero no destruiré por completo la casa de Jacob.",
            "Yo, el Señor, lo afirmo."
          ],
          "rlw_lines": []
        },
        {
          "type": "verse",
          "verse_numbers": [
            9
          ],
          "lines": [
            "Voy a ordenar que la casa de Israel sea zarandeada",
            "como se zarandea el trigo en una criba,",
            "sin que un solo grano caiga a tierra."
          ],
          "rlw_lines": []
        },
        {
          "type": "verse",
          "verse_numbers": [
            10
          ],
          "lines": [
            "Todos los pecadores de mi pueblo",
            "morirán a filo de espada;",
            "todos los que dicen: “Nada de eso nos pasará;",
            "el mal no va a alcanzarnos.”"
          ],
          "rlw_lines": []
        },
        {
          "type": "heading2",
          "verse_numbers": [],
          "lines": [
            "V. EPÍLOGO"
          ],
          "rlw_lines": []
        },
        {
          "type": "section2",
          "verse_numbers": [],
          "lines": [
            "(9.11-15)"
          ],
          "rlw_lines": []
        },
        {
          "type": "heading1",
          "verse_numbers": [],
          "lines": [
            "Restauración futura de Israel"
          ],
          "rlw_lines": []
        },
        {
          "type": "verse",
          "verse_numbers": [
            11
          ],
          "lines": [
            "»El día viene en que levantaré la caída choza de David. Taparé sus brechas, levantaré sus ruinas y la reconstruiré tal como fue en los tiempos pasados,"
          ],
          "rlw_lines": []
        },
        {
          "type": "verse",
          "verse_numbers": [
            12
          ],
          "lines": [
            "para que lo que quede de Edom y de toda nación que me ha pertenecido vuelva a ser posesión de Israel.» El Señor ha dado su palabra, y la cumplirá."
          ],
          "rlw_lines": []
        },
        {
          "type": "verse",
          "verse_numbers": [
            13
          ],
          "lines": [
            "«Vienen días en que todavía se estará cosechando el trigo cuando ya será tiempo de arar el campo, y en que aún no se habrá acabado de pisar las uvas cuando ya será tiempo de sembrar el trigo. Por montes y colinas correrá el vino como agua."
          ],
          "rlw_lines": []
        },
        {
          "type": "verse",
          "verse_numbers": [
            14
          ],
          "lines": [
            "Entonces traeré del destierro a mi pueblo Israel. Reconstruirán las ciudades destruidas, y vivirán en ellas; plantarán viñedos, y beberán su vino; sembrarán huertos, y comerán sus frutos."
          ],
          "rlw_lines": []
        },
        {
          "type": "verse",
          "verse_numbers": [
            15
          ],
          "lines": [
            "Pues los plantaré en su propia tierra, y nunca más volverán a ser arrancados de la tierra que les di.» Dios el Señor lo afirma."
          ],
          "rlw_lines": []
        }
      ]
    }
  ]
}